README.md
setup.py
fast/__init__.py
fast.egg-info/PKG-INFO
fast.egg-info/SOURCES.txt
fast.egg-info/dependency_links.txt
fast.egg-info/top_level.txt