Metadata-Version: 2.1
Name: fast
Version: 3.0.0
Summary: Fast format for storing AI training data.
Home-page: http://github.com/danijar/fast
Classifier: Intended Audience :: Science/Research
Classifier: License :: OSI Approved :: MIT License
Classifier: Programming Language :: Python :: 3
